secp256k1py/__init__.py
secp256k1py/secp256k1.py
savingsatoshi_secp256k1py-0.2.0.dist-info/METADATA
savingsatoshi_secp256k1py-0.2.0.dist-info/WHEEL
savingsatoshi_secp256k1py-0.2.0.dist-info/RECORD
