Metadata-Version: 2.1
Name: savingsatoshi_secp256k1py
Version: 0.2.0
Summary: ECDSA module for Saving Satoshi code challenges
License: MIT
Author: Matthew Zipkin
Author-email: pinheadmz@gmail.com
Requires-Python: >=3.11,<4.0
Classifier: License :: OSI Approved :: MIT License
Classifier: Programming Language :: Python :: 3
Classifier: Programming Language :: Python :: 3.11
Classifier: Programming Language :: Python :: 3.12
